[
    {
        "time": "2024-07-15",
        "htmlContent": "Two papers got accepted into IEEE VIS! Check out <a class='normal-a news-paper-nickname' href='./publication#2024-vila'>vila</a> and <a class='normal-a news-paper-nickname' href='./publication#2024-backstory'>backstory</a>."
    },
    {
        "time": "2024-07-14",
        "htmlContent": "Finished the first version of this website! "
    },
    {
        "time": "2024-06-25",
        "htmlContent": "Fumeng accepted the job offer and initialized this website. &#x263A;"
    }
]
